pvoutput/__init__.py
pvoutput/consts.py
pvoutput/daterange.py
pvoutput/exceptions.py
pvoutput/mapscraper.py
pvoutput/prcoess.py
pvoutput/pvoutput.py
pvoutput/utils.py
pvoutput/grid_search/__init__.py
pvoutput/grid_search/app.py
pvoutput/grid_search/clip.py
pvoutput/grid_search/grid_search.py
pvoutput/grid_search/natural_earth.py
pvoutput_ocf-0.1.39.dist-info/licenses/LICENSE.txt
tests/__init__.py
tests/conftest.py
tests/test_daterange.py
tests/test_grid_search.py
tests/test_mapscraper.py
tests/test_process.py
tests/test_pvoutput.py
tests/test_utils.py
pvoutput_ocf-0.1.39.dist-info/METADATA
pvoutput_ocf-0.1.39.dist-info/WHEEL
pvoutput_ocf-0.1.39.dist-info/top_level.txt
pvoutput_ocf-0.1.39.dist-info/RECORD
