Metadata-Version: 2.4
Name: pvoutput-ocf
Version: 0.1.39
Author-email: info@openclimatefix.org
License: MIT
License-File: LICENSE.txt
Requires-Dist: numpy
Requires-Dist: pandas
Requires-Dist: pyproj
Requires-Dist: pyshp
Requires-Dist: shapely
Requires-Dist: cython>0.15.1
Requires-Dist: geopandas
Requires-Dist: pytest
Requires-Dist: pyyaml
Requires-Dist: tables
Requires-Dist: matplotlib
Requires-Dist: jupyter
Requires-Dist: urllib3
Requires-Dist: requests
Requires-Dist: beautifulsoup4
Dynamic: author-email
Dynamic: description
Dynamic: description-content-type
Dynamic: license
Dynamic: license-file
Dynamic: requires-dist
